MANIFEST.in
README.txt
setup.cfg
setup.py
docs/HISTORY.txt
horae/__init__.py
horae.groupselect.egg-info/PKG-INFO
horae.groupselect.egg-info/SOURCES.txt
horae.groupselect.egg-info/dependency_links.txt
horae.groupselect.egg-info/entry_points.txt
horae.groupselect.egg-info/namespace_packages.txt
horae.groupselect.egg-info/not-zip-safe
horae.groupselect.egg-info/requires.txt
horae.groupselect.egg-info/top_level.txt
horae/groupselect/__init__.py
horae/groupselect/configure.zcml
horae/groupselect/field.py
horae/groupselect/interfaces.py
horae/groupselect/widgets.py