Metadata-Version: 1.0
Name: horae.groupselect
Version: 1.0a1
Summary: Provides a grouped Dropdown widget for zope.formlib
Home-page: UNKNOWN
Author: Simon Kaeser
Author-email: skaeser@gmail.com
License: GPL
Platform: UNKNOWN
Classifier: Programming Language :: Python
Classifier: Topic :: Software Development :: Libraries :: Python Modules
